CHANGELOG.txt
LICENCE.txt
MANIFEST.in
README.txt
setup.py
Generador_Nombre/__init__.py
Generador_Nombre/pytransform/__init__.py
Generador_Nombre/pytransform/_pytransform.dll
Generator_Name.egg-info/PKG-INFO
Generator_Name.egg-info/SOURCES.txt
Generator_Name.egg-info/dependency_links.txt
Generator_Name.egg-info/top_level.txt