Metadata-Version: 1.1
Name: Generator-Name
Version: 0.0.3
Summary: Generacion de Id en base a nombre
Home-page: UNKNOWN
Author: Ari Bautista
Author-email: aribautista66@gmail.com
License: MIT
Keywords: Login
Platform: UNKNOWN
Classifier: Development Status :: 5 - Production/Stable
Classifier: Intended Audience :: Education
Classifier: Operating System :: Microsoft :: Windows :: Windows 10
Classifier: License :: OSI Approved :: MIT License
Classifier: Programming Language :: Python :: 3
